ALU_4bit/ALU_4.v
module ALU_4 (
    input [3:0] a,b,
    input [2:0] sel,
    output reg[7:0] out
    );

    always @(*) begin
        case (sel)
            3'b000: out = a + b;
            3'b001: out = a - b;
            3'b010: out = a * b;
            3'b011: out = a % b;
            3'b100: out = a & b; 
            3'b101: out = a | b;
            3'b110: out = a ^ b;
            3'b111: out = a ~^ b;
            default: out = 8'b0;
        endcase
    end

endmodule

ALU_4bit/tb_ALU_4.v
module tb_ALU_4;
    reg [3:0] a, b;
    reg [2:0] sel;
    wire [7:0] out;

    integer i,j,k;

    ALU_4 uut(
        .a(a), .b(b), .sel(sel),
        .out(out)
    );

    initial begin
        $dumpfile("ALU_4.vcd");
        $dumpvars(0, tb_ALU_4);

        for(k=0; k<8; k+=1) begin
            sel = k;
            for(i=0; i<16; i+=1) begin
                for(j=0; j<16; j+=1) begin
                a = i; b = j;
                #10;
                end
            end
        end
        $display("Verification Done!");
        $finish;
    end
/* Instead of writing 8 loops we worked with 3 loops........
sel = 3'b000;
        for(i=0; i<16; i+=1) begin
            for(j=0; j<16; j+=1) begin
                a = i; b = j;
                #10;
            end
        end

        sel = 3'b001;
        for(i=0; i<16; i+=1) begin
            for(j=0; j<16; j+=1) begin
                a=i; b=j;
                #10;
            end
        end
        sel = 3'b010;
        for(i=0; i<16; i+=1) begin
            for(j=0; j<16; j+=1) begin
                a = i; b = j;
                #10;
            end
        end
        sel = 3'b011;
        for(i=0; i<16; i+=1) begin
            for(j=0; j<16; j+=1) begin
                a = i; b = j;
                #10;
            end
        end
        sel = 3'b100;
        for(i=0; i<16; i+=1) begin
            for(j=0; j<16; j+=1) begin
                a = i; b = j;
                #10;
            end
        end
        sel = 3'b101;
        for(i=0; i<16; i+=1) begin
            for(j=0; j<16; j+=1) begin
                a = i; b = j;
                #10;
            end
        end
        sel = 3'b110;
        for(i=0; i<16; i+=1) begin
            for(j=0; j<16; j+=1) begin
                a = i; b = j;
                #10;
            end
        end
        sel = 3'b111;
        for(i=0; i<16; i+=1) begin
            for(j=0; j<16; j+=1) begin
                a = i; b = j;
                #10;
            end
        end
*/
endmodule

ALU_4bit/ALU_4.vcd
$date
	Sun May 10 06:56:00 2026
$end
$version
	Icarus Verilog
$end
$timescale
	1s
$end
$scope module tb_ALU_4 $end
$var wire 8 ! out [7:0] $end
$var reg 4 " a [3:0] $end
$var reg 4 # b [3:0] $end
$var reg 3 $ sel [2:0] $end
$var integer 32 % i [31:0] $end
$var integer 32 & j [31:0] $end
$var integer 32 ' k [31:0] $end
$scope module uut $end
$var wire 4 ( a [3:0] $end
$var wire 4 ) b [3:0] $end
$var wire 3 * sel [2:0] $end
$var reg 8 + out [7:0] $end
$upscope $end
$upscope $end
$enddefinitions $end
$comment Show the parameter values. $end
$dumpall
$end
#0
$dumpvars
b0 +
b0 *
b0 )
b0 (
b0 '
b0 &
b0 %
b0 $
b0 #
b0 "
b0 !
$end
#10
b1 !
b1 +
b1 #
b1 )
b1 &
#20
b10 !
b10 +
b10 #
b10 )
b10 &
#30
b11 !
b11 +
b11 #
b11 )
b11 &
#40
b100 !
b100 +
b100 #
b100 )
b100 &
#50
b101 !
b101 +
b101 #
b101 )
b101 &
#60
b110 !
b110 +
b110 #
b110 )
b110 &
#70
b111 !
b111 +
b111 #
b111 )
b111 &
#80
b1000 !
b1000 +
b1000 #
b1000 )
b1000 &
#90
b1001 !
b1001 +
b1001 #
b1001 )
b1001 &
#100
b1010 !
b1010 +
b1010 #
b1010 )
b1010 &
#110
b1011 !
b1011 +
b1011 #
b1011 )
b1011 &
#120
b1100 !
b1100 +
b1100 #
b1100 )
b1100 &
#130
b1101 !
b1101 +
b1101 #
b1101 )
b1101 &
#140
b1110 !
b1110 +
b1110 #
b1110 )
b1110 &
#150
b1111 !
b1111 +
b1111 #
b1111 )
b1111 &
#160
b1 !
b1 +
b0 #
b0 )
b1 "
b1 (
b1 %
b0 &
#170
b10 !
b10 +
b1 #
b1 )
b1 &
#180
b11 !
b11 +
b10 #
b10 )
b10 &
#190
b100 !
b100 +
b11 #
b11 )
b11 &
#200
b101 !
b101 +
b100 #
b100 )
b100 &
#210
b110 !
b110 +
b101 #
b101 )
b101 &
#220
b111 !
b111 +
b110 #
b110 )
b110 &
#230
b1000 !
b1000 +
b111 #
b111 )
b111 &
#240
b1001 !
b1001 +
b1000 #
b1000 )
b1000 &
#250
b1010 !
b1010 +
b1001 #
b1001 )
b1001 &
#260
b1011 !
b1011 +
b1010 #
b1010 )
b1010 &
#270
b1100 !
b1100 +
b1011 #
b1011 )
b1011 &
#280
b1101 !
b1101 +
b1100 #
b1100 )
b1100 &
#290
b1110 !
b1110 +
b1101 #
b1101 )
b1101 &
#300
b1111 !
b1111 +
b1110 #
b1110 )
b1110 &
#310
b10000 !
b10000 +
b1111 #
b1111 )
b1111 &
#320
b10 !
b10 +
b0 #
b0 )
b10 "
b10 (
b10 %
b0 &
#330
b11 !
b11 +
b1 #
b1 )
b1 &
#340
b100 !
b100 +
b10 #
b10 )
b10 &
#350
b101 !
b101 +
b11 #
b11 )
b11 &
#360
b110 !
b110 +
b100 #
b100 )
b100 &
#370
b111 !
b111 +
b101 #
b101 )
b101 &
#380
b1000 !
b1000 +
b110 #
b110 )
b110 &
#390
b1001 !
b1001 +
b111 #
b111 )
b111 &
#400
b1010 !
b1010 +
b1000 #
b1000 )
b1000 &
#410
b1011 !
b1011 +
b1001 #
b1001 )
b1001 &
#420
b1100 !
b1100 +
b1010 #
b1010 )
b1010 &
#430
b1101 !
b1101 +
b1011 #
b1011 )
b1011 &
#440
b1110 !
b1110 +
b1100 #
b1100 )
b1100 &
#450
b1111 !
b1111 +
b1101 #
b1101 )
b1101 &
#460
b10000 !
b10000 +
b1110 #
b1110 )
b1110 &
#470
b10001 !
b10001 +
b1111 #
b1111 )
b1111 &
#480
b11 !
b11 +
b0 #
b0 )
b11 "
b11 (
b11 %
b0 &
#490
b100 !
b100 +
b1 #
b1 )
b1 &
#500
b101 !
b101 +
b10 #
b10 )
b10 &
#510
b110 !
b110 +
b11 #
b11 )
b11 &
#520
b111 !
b111 +
b100 #
b100 )
b100 &
#530
b1000 !
b1000 +
b101 #
b101 )
b101 &
#540
b1001 !
b1001 +
b110 #
b110 )
b110 &
#550
b1010 !
b1010 +
b111 #
b111 )
b111 &
#560
b1011 !
b1011 +
b1000 #
b1000 )
b1000 &
#570
b1100 !
b1100 +
b1001 #
b1001 )
b1001 &
#580
b1101 !
b1101 +
b1010 #
b1010 )
b1010 &
#590
b1110 !
b1110 +
b1011 #
b1011 )
b1011 &
#600
b1111 !
b1111 +
b1100 #
b1100 )
b1100 &
#610
b10000 !
b10000 +
b1101 #
b1101 )
b1101 &
#620
b10001 !
b10001 +
b1110 #
b1110 )
b1110 &
#630
b10010 !
b10010 +
b1111 #
b1111 )
b1111 &
#640
b100 !
b100 +
b0 #
b0 )
b100 "
b100 (
b100 %
b0 &
#650
b101 !
b101 +
b1 #
b1 )
b1 &
#660
b110 !
b110 +
b10 #
b10 )
b10 &
#670
b111 !
b111 +
b11 #
b11 )
b11 &
#680
b1000 !
b1000 +
b100 #
b100 )
b100 &
#690
b1001 !
b1001 +
b101 #
b101 )
b101 &
#700
b1010 !
b1010 +
b110 #
b110 )
b110 &
#710
b1011 !
b1011 +
b111 #
b111 )
b111 &
#720
b1100 !
b1100 +
b1000 #
b1000 )
b1000 &
#730
b1101 !
b1101 +
b1001 #
b1001 )
b1001 &
#740
b1110 !
b1110 +
b1010 #
b1010 )
b1010 &
#750
b1111 !
b1111 +
b1011 #
b1011 )
b1011 &
#760
b10000 !
b10000 +
b1100 #
b1100 )
b1100 &
#770
b10001 !
b10001 +
b1101 #
b1101 )
b1101 &
#780
b10010 !
b10010 +
b1110 #
b1110 )
b1110 &
#790
b10011 !
b10011 +
b1111 #
b1111 )
b1111 &
#800
b101 !
b101 +
b0 #
b0 )
b101 "
b101 (
b101 %
b0 &
#810
b110 !
b110 +
b1 #
b1 )
b1 &
#820
b111 !
b111 +
b10 #
b10 )
b10 &
#830
b1000 !
b1000 +
b11 #
b11 )
b11 &
#840
b1001 !
b1001 +
b100 #
b100 )
b100 &
#850
b1010 !
b1010 +
b101 #
b101 )
b101 &
#860
b1011 !
b1011 +
b110 #
b110 )
b110 &
#870
b1100 !
b1100 +
b111 #
b111 )
b111 &
#880
b1101 !
b1101 +
b1000 #
b1000 )
b1000 &
#890
b1110 !
b1110 +
b1001 #
b1001 )
b1001 &
#900
b1111 !
b1111 +
b1010 #
b1010 )
b1010 &
#910
b10000 !
b10000 +
b1011 #
b1011 )
b1011 &
#920
b10001 !
b10001 +
b1100 #
b1100 )
b1100 &
#930
b10010 !
b10010 +
b1101 #
b1101 )
b1101 &
#940
b10011 !
b10011 +
b1110 #
b1110 )
b1110 &
#950
b10100 !
b10100 +
b1111 #
b1111 )
b1111 &
#960
b110 !
b110 +
b0 #
b0 )
b110 "
b110 (
b110 %
b0 &
#970
b111 !
b111 +
b1 #
b1 )
b1 &
#980
b1000 !
b1000 +
b10 #
b10 )
b10 &
#990
b1001 !
b1001 +
b11 #
b11 )
b11 &
#1000
b1010 !
b1010 +
b100 #
b100 )
b100 &
#1010
b1011 !
b1011 +
b101 #
b101 )
b101 &
#1020
b1100 !
b1100 +
b110 #
b110 )
b110 &
#1030
b1101 !
b1101 +
b111 #
b111 )
b111 &
#1040
b1110 !
b1110 +
b1000 #
b1000 )
b1000 &
#1050
b1111 !
b1111 +
b1001 #
b1001 )
b1001 &
#1060
b10000 !
b10000 +
b1010 #
b1010 )
b1010 &
#1070
b10001 !
b10001 +
b1011 #
b1011 )
b1011 &
#1080
b10010 !
b10010 +
b1100 #
b1100 )
b1100 &
#1090
b10011 !
b10011 +
b1101 #
b1101 )
b1101 &
#1100
b10100 !
b10100 +
b1110 #
b1110 )
b1110 &
#1110
b10101 !
b10101 +
b1111 #
b1111 )
b1111 &
#1120
b111 !
b111 +
b0 #
b0 )
b111 "
b111 (
b111 %
b0 &
#1130
b1000 !
b1000 +
b1 #
b1 )
b1 &
#1140
b1001 !
b1001 +
b10 #
b10 )
b10 &
#1150
b1010 !
b1010 +
b11 #
b11 )
b11 &
#1160
b1011 !
b1011 +
b100 #
b100 )
b100 &
#1170
b1100 !
b1100 +
b101 #
b101 )
b101 &
#1180
b1101 !
b1101 +
b110 #
b110 )
b110 &
#1190
b1110 !
b1110 +
b111 #
b111 )
b111 &
#1200
b1111 !
b1111 +
b1000 #
b1000 )
b1000 &
#1210
b10000 !
b10000 +
b1001 #
b1001 )
b1001 &
#1220
b10001 !
b10001 +
b1010 #
b1010 )
b1010 &
#1230
b10010 !
b10010 +
b1011 #
b1011 )
b1011 &
#1240
b10011 !
b10011 +
b1100 #
b1100 )
b1100 &
#1250
b10100 !
b10100 +
b1101 #
b1101 )
b1101 &
#1260
b10101 !
b10101 +
b1110 #
b1110 )
b1110 &
#1270
b10110 !
b10110 +
b1111 #
b1111 )
b1111 &
#1280
b1000 !
b1000 +
b0 #
b0 )
b1000 "
b1000 (
b1000 %
b0 &
#1290
b1001 !
b1001 +
b1 #
b1 )
b1 &
#1300
b1010 !
b1010 +
b10 #
b10 )
b10 &
#1310
b1011 !
b1011 +
b11 #
b11 )
b11 &
#1320
b1100 !
b1100 +
b100 #
b100 )
b100 &
#1330
b1101 !
b1101 +
b101 #
b101 )
b101 &
#1340
b1110 !
b1110 +
b110 #
b110 )
b110 &
#1350
b1111 !
b1111 +
b111 #
b111 )
b111 &
#1360
b10000 !
b10000 +
b1000 #
b1000 )
b1000 &
#1370
b10001 !
b10001 +
b1001 #
b1001 )
b1001 &
#1380
b10010 !
b10010 +
b1010 #
b1010 )
b1010 &
#1390
b10011 !
b10011 +
b1011 #
b1011 )
b1011 &
#1400
b10100 !
b10100 +
b1100 #
b1100 )
b1100 &
#1410
b10101 !
b10101 +
b1101 #
b1101 )
b1101 &
#1420
b10110 !
b10110 +
b1110 #
b1110 )
b1110 &
#1430
b10111 !
b10111 +
b1111 #
b1111 )
b1111 &
#1440
b1001 !
b1001 +
b0 #
b0 )
b1001 "
b1001 (
b1001 %
b0 &
#1450
b1010 !
b1010 +
b1 #
b1 )
b1 &
#1460
b1011 !
b1011 +
b10 #
b10 )
b10 &
#1470
b1100 !
b1100 +
b11 #
b11 )
b11 &
#1480
b1101 !
b1101 +
b100 #
b100 )
b100 &
#1490
b1110 !
b1110 +
b101 #
b101 )
b101 &
#1500
b1111 !
b1111 +
b110 #
b110 )
b110 &
#1510
b10000 !
b10000 +
b111 #
b111 )
b111 &
#1520
b10001 !
b10001 +
b1000 #
b1000 )
b1000 &
#1530
b10010 !
b10010 +
b1001 #
b1001 )
b1001 &
#1540
b10011 !
b10011 +
b1010 #
b1010 )
b1010 &
#1550
b10100 !
b10100 +
b1011 #
b1011 )
b1011 &
#1560
b10101 !
b10101 +
b1100 #
b1100 )
b1100 &
#1570
b10110 !
b10110 +
b1101 #
b1101 )
b1101 &
#1580
b10111 !
b10111 +
b1110 #
b1110 )
b1110 &
#1590
b11000 !
b11000 +
b1111 #
b1111 )
b1111 &
#1600
b1010 !
b1010 +
b0 #
b0 )
b1010 "
b1010 (
b1010 %
b0 &
#1610
b1011 !
b1011 +
b1 #
b1 )
b1 &
#1620
b1100 !
b1100 +
b10 #
b10 )
b10 &
#1630
b1101 !
b1101 +
b11 #
b11 )
b11 &
#1640
b1110 !
b1110 +
b100 #
b100 )
b100 &
#1650
b1111 !
b1111 +
b101 #
b101 )
b101 &
#1660
b10000 !
b10000 +
b110 #
b110 )
b110 &
#1670
b10001 !
b10001 +
b111 #
b111 )
b111 &
#1680
b10010 !
b10010 +
b1000 #
b1000 )
b1000 &
#1690
b10011 !
b10011 +
b1001 #
b1001 )
b1001 &
#1700
b10100 !
b10100 +
b1010 #
b1010 )
b1010 &
#1710
b10101 !
b10101 +
b1011 #
b1011 )
b1011 &
#1720
b10110 !
b10110 +
b1100 #
b1100 )
b1100 &
#1730
b10111 !
b10111 +
b1101 #
b1101 )
b1101 &
#1740
b11000 !
b11000 +
b1110 #
b1110 )
b1110 &
#1750
b11001 !
b11001 +
b1111 #
b1111 )
b1111 &
#1760
b1011 !
b1011 +
b0 #
b0 )
b1011 "
b1011 (
b1011 %
b0 &
#1770
b1100 !
b1100 +
b1 #
b1 )
b1 &
#1780
b1101 !
b1101 +
b10 #
b10 )
b10 &
#1790
b1110 !
b1110 +
b11 #
b11 )
b11 &
#1800
b1111 !
b1111 +
b100 #
b100 )
b100 &
#1810
b10000 !
b10000 +
b101 #
b101 )
b101 &
#1820
b10001 !
b10001 +
b110 #
b110 )
b110 &
#1830
b10010 !
b10010 +
b111 #
b111 )
b111 &
#1840
b10011 !
b10011 +
b1000 #
b1000 )
b1000 &
#1850
b10100 !
b10100 +
b1001 #
b1001 )
b1001 &
#1860
b10101 !
b10101 +
b1010 #
b1010 )
b1010 &
#1870
b10110 !
b10110 +
b1011 #
b1011 )
b1011 &
#1880
b10111 !
b10111 +
b1100 #
b1100 )
b1100 &
#1890
b11000 !
b11000 +
b1101 #
b1101 )
b1101 &
#1900
b11001 !
b11001 +
b1110 #
b1110 )
b1110 &
#1910
b11010 !
b11010 +
b1111 #
b1111 )
b1111 &
#1920
b1100 !
b1100 +
b0 #
b0 )
b1100 "
b1100 (
b1100 %
b0 &
#1930
b1101 !
b1101 +
b1 #
b1 )
b1 &
#1940
b1110 !
b1110 +
b10 #
b10 )
b10 &
#1950
b1111 !
b1111 +
b11 #
b11 )
b11 &
#1960
b10000 !
b10000 +
b100 #
b100 )
b100 &
#1970
b10001 !
b10001 +
b101 #
b101 )
b101 &
#1980
b10010 !
b10010 +
b110 #
b110 )
b110 &
#1990
b10011 !
b10011 +
b111 #
b111 )
b111 &
#2000
b10100 !
b10100 +
b1000 #
b1000 )
b1000 &
#2010
b10101 !
b10101 +
b1001 #
b1001 )
b1001 &
#2020
b10110 !
b10110 +
b1010 #
b1010 )
b1010 &
#2030
b10111 !
b10111 +
b1011 #
b1011 )
b1011 &
#2040
b11000 !
b11000 +
b1100 #
b1100 )
b1100 &
#2050
b11001 !
b11001 +
b1101 #
b1101 )
b1101 &
#2060
b11010 !
b11010 +
b1110 #
b1110 )
b1110 &
#2070
b11011 !
b11011 +
b1111 #
b1111 )
b1111 &
#2080
b1101 !
b1101 +
b0 #
b0 )
b1101 "
b1101 (
b1101 %
b0 &
#2090
b1110 !
b1110 +
b1 #
b1 )
b1 &
#2100
b1111 !
b1111 +
b10 #
b10 )
b10 &
#2110
b10000 !
b10000 +
b11 #
b11 )
b11 &
#2120
b10001 !
b10001 +
b100 #
b100 )
b100 &
#2130
b10010 !
b10010 +
b101 #
b101 )
b101 &
#2140
b10011 !
b10011 +
b110 #
b110 )
b110 &
#2150
b10100 !
b10100 +
b111 #
b111 )
b111 &
#2160
b10101 !
b10101 +
b1000 #
b1000 )
b1000 &
#2170
b10110 !
b10110 +
b1001 #
b1001 )
b1001 &
#2180
b10111 !
b10111 +
b1010 #
b1010 )
b1010 &
#2190
b11000 !
b11000 +
b1011 #
b1011 )
b1011 &
#2200
b11001 !
b11001 +
b1100 #
b1100 )
b1100 &
#2210
b11010 !
b11010 +
b1101 #
b1101 )
b1101 &
#2220
b11011 !
b11011 +
b1110 #
b1110 )
b1110 &
#2230
b11100 !
b11100 +
b1111 #
b1111 )
b1111 &
#2240
b1110 !
b1110 +
b0 #
b0 )
b1110 "
b1110 (
b1110 %
b0 &
#2250
b1111 !
b1111 +
b1 #
b1 )
b1 &
#2260
b10000 !
b10000 +
b10 #
b10 )
b10 &
#2270
b10001 !
b10001 +
b11 #
b11 )
b11 &
#2280
b10010 !
b10010 +
b100 #
b100 )
b100 &
#2290
b10011 !
b10011 +
b101 #
b101 )
b101 &
#2300
b10100 !
b10100 +
b110 #
b110 )
b110 &
#2310
b10101 !
b10101 +
b111 #
b111 )
b111 &
#2320
b10110 !
b10110 +
b1000 #
b1000 )
b1000 &
#2330
b10111 !
b10111 +
b1001 #
b1001 )
b1001 &
#2340
b11000 !
b11000 +
b1010 #
b1010 )
b1010 &
#2350
b11001 !
b11001 +
b1011 #
b1011 )
b1011 &
#2360
b11010 !
b11010 +
b1100 #
b1100 )
b1100 &
#2370
b11011 !
b11011 +
b1101 #
b1101 )
b1101 &
#2380
b11100 !
b11100 +
b1110 #
b1110 )
b1110 &
#2390
b11101 !
b11101 +
b1111 #
b1111 )
b1111 &
#2400
b1111 !
b1111 +
b0 #
b0 )
b1111 "
b1111 (
b1111 %
b0 &
#2410
b10000 !
b10000 +
b1 #
b1 )
b1 &
#2420
b10001 !
b10001 +
b10 #
b10 )
b10 &
#2430
b10010 !
b10010 +
b11 #
b11 )
b11 &
#2440
b10011 !
b10011 +
b100 #
b100 )
b100 &
#2450
b10100 !
b10100 +
b101 #
b101 )
b101 &
#2460
b10101 !
b10101 +
b110 #
b110 )
b110 &
#2470
b10110 !
b10110 +
b111 #
b111 )
b111 &
#2480
b10111 !
b10111 +
b1000 #
b1000 )
b1000 &
#2490
b11000 !
b11000 +
b1001 #
b1001 )
b1001 &
#2500
b11001 !
b11001 +
b1010 #
b1010 )
b1010 &
#2510
b11010 !
b11010 +
b1011 #
b1011 )
b1011 &
#2520
b11011 !
b11011 +
b1100 #
b1100 )
b1100 &
#2530
b11100 !
b11100 +
b1101 #
b1101 )
b1101 &
#2540
b11101 !
b11101 +
b1110 #
b1110 )
b1110 &
#2550
b11110 !
b11110 +
b1111 #
b1111 )
b1111 &
#2560
b0 !
b0 +
b0 #
b0 )
b0 "
b0 (
b1 $
b1 *
b1 '
b0 %
b0 &
#2570
b11111111 !
b11111111 +
b1 #
b1 )
b1 &
#2580
b11111110 !
b11111110 +
b10 #
b10 )
b10 &
#2590
b11111101 !
b11111101 +
b11 #
b11 )
b11 &
#2600
b11111100 !
b11111100 +
b100 #
b100 )
b100 &
#2610
b11111011 !
b11111011 +
b101 #
b101 )
b101 &
#2620
b11111010 !
b11111010 +
b110 #
b110 )
b110 &
#2630
b11111001 !
b11111001 +
b111 #
b111 )
b111 &
#2640
b11111000 !
b11111000 +
b1000 #
b1000 )
b1000 &
#2650
b11110111 !
b11110111 +
b1001 #
b1001 )
b1001 &
#2660
b11110110 !
b11110110 +
b1010 #
b1010 )
b1010 &
#2670
b11110101 !
b11110101 +
b1011 #
b1011 )
b1011 &
#2680
b11110100 !
b11110100 +
b1100 #
b1100 )
b1100 &
#2690
b11110011 !
b11110011 +
b1101 #
b1101 )
b1101 &
#2700
b11110010 !
b11110010 +
b1110 #
b1110 )
b1110 &
#2710
b11110001 !
b11110001 +
b1111 #
b1111 )
b1111 &
#2720
b1 !
b1 +
b0 #
b0 )
b1 "
b1 (
b1 %
b0 &
#2730
b0 !
b0 +
b1 #
b1 )
b1 &
#2740
b11111111 !
b11111111 +
b10 #
b10 )
b10 &
#2750
b11111110 !
b11111110 +
b11 #
b11 )
b11 &
#2760
b11111101 !
b11111101 +
b100 #
b100 )
b100 &
#2770
b11111100 !
b11111100 +
b101 #
b101 )
b101 &
#2780
b11111011 !
b11111011 +
b110 #
b110 )
b110 &
#2790
b11111010 !
b11111010 +
b111 #
b111 )
b111 &
#2800
b11111001 !
b11111001 +
b1000 #
b1000 )
b1000 &
#2810
b11111000 !
b11111000 +
b1001 #
b1001 )
b1001 &
#2820
b11110111 !
b11110111 +
b1010 #
b1010 )
b1010 &
#2830
b11110110 !
b11110110 +
b1011 #
b1011 )
b1011 &
#2840
b11110101 !
b11110101 +
b1100 #
b1100 )
b1100 &
#2850
b11110100 !
b11110100 +
b1101 #
b1101 )
b1101 &
#2860
b11110011 !
b11110011 +
b1110 #
b1110 )
b1110 &
#2870
b11110010 !
b11110010 +
b1111 #
b1111 )
b1111 &
#2880
b10 !
b10 +
b0 #
b0 )
b10 "
b10 (
b10 %
b0 &
#2890
b1 !
b1 +
b1 #
b1 )
b1 &
#2900
b0 !
b0 +
b10 #
b10 )
b10 &
#2910
b11111111 !
b11111111 +
b11 #
b11 )
b11 &
#2920
b11111110 !
b11111110 +
b100 #
b100 )
b100 &
#2930
b11111101 !
b11111101 +
b101 #
b101 )
b101 &
#2940
b11111100 !
b11111100 +
b110 #
b110 )
b110 &
#2950
b11111011 !
b11111011 +
b111 #
b111 )
b111 &
#2960
b11111010 !
b11111010 +
b1000 #
b1000 )
b1000 &
#2970
b11111001 !
b11111001 +
b1001 #
b1001 )
b1001 &
#2980
b11111000 !
b11111000 +
b1010 #
b1010 )
b1010 &
#2990
b11110111 !
b11110111 +
b1011 #
b1011 )
b1011 &
#3000
b11110110 !
b11110110 +
b1100 #
b1100 )
b1100 &
#3010
b11110101 !
b11110101 +
b1101 #
b1101 )
b1101 &
#3020
b11110100 !
b11110100 +
b1110 #
b1110 )
b1110 &
#3030
b11110011 !
b11110011 +
b1111 #
b1111 )
b1111 &
#3040
b11 !
b11 +
b0 #
b0 )
b11 "
b11 (
b11 %
b0 &
#3050
b10 !
b10 +
b1 #
b1 )
b1 &
#3060
b1 !
b1 +
b10 #
b10 )
b10 &
#3070
b0 !
b0 +
b11 #
b11 )
b11 &
#3080
b11111111 !
b11111111 +
b100 #
b100 )
b100 &
#3090
b11111110 !
b11111110 +
b101 #
b101 )
b101 &
#3100
b11111101 !
b11111101 +
b110 #
b110 )
b110 &
#3110
b11111100 !
b11111100 +
b111 #
b111 )
b111 &
#3120
b11111011 !
b11111011 +
b1000 #
b1000 )
b1000 &
#3130
b11111010 !
b11111010 +
b1001 #
b1001 )
b1001 &
#3140
b11111001 !
b11111001 +
b1010 #
b1010 )
b1010 &
#3150
b11111000 !
b11111000 +
b1011 #
b1011 )
b1011 &
#3160
b11110111 !
b11110111 +
b1100 #
b1100 )
b1100 &
#3170
b11110110 !
b11110110 +
b1101 #
b1101 )
b1101 &
#3180
b11110101 !
b11110101 +
b1110 #
b1110 )
b1110 &
#3190
b11110100 !
b11110100 +
b1111 #
b1111 )
b1111 &
#3200
b100 !
b100 +
b0 #
b0 )
b100 "
b100 (
b100 %
b0 &
#3210
b11 !
b11 +
b1 #
b1 )
b1 &
#3220
b10 !
b10 +
b10 #
b10 )
b10 &
#3230
b1 !
b1 +
b11 #
b11 )
b11 &
#3240
b0 !
b0 +
b100 #
b100 )
b100 &
#3250
b11111111 !
b11111111 +
b101 #
b101 )
b101 &
#3260
b11111110 !
b11111110 +
b110 #
b110 )
b110 &
#3270
b11111101 !
b11111101 +
b111 #
b111 )
b111 &
#3280
b11111100 !
b11111100 +
b1000 #
b1000 )
b1000 &
#3290
b11111011 !
b11111011 +
b1001 #
b1001 )
b1001 &
#3300
b11111010 !
b11111010 +
b1010 #
b1010 )
b1010 &
#3310
b11111001 !
b11111001 +
b1011 #
b1011 )
b1011 &
#3320
b11111000 !
b11111000 +
b1100 #
b1100 )
b1100 &
#3330
b11110111 !
b11110111 +
b1101 #
b1101 )
b1101 &
#3340
b11110110 !
b11110110 +
b1110 #
b1110 )
b1110 &
#3350
b11110101 !
b11110101 +
b1111 #
b1111 )
b1111 &
#3360
b101 !
b101 +
b0 #
b0 )
b101 "
b101 (
b101 %
b0 &
#3370
b100 !
b100 +
b1 #
b1 )
b1 &
#3380
b11 !
b11 +
b10 #
b10 )
b10 &
#3390
b10 !
b10 +
b11 #
b11 )
b11 &
#3400
b1 !
b1 +
b100 #
b100 )
b100 &
#3410
b0 !
b0 +
b101 #
b101 )
b101 &
#3420
b11111111 !
b11111111 +
b110 #
b110 )
b110 &
#3430
b11111110 !
b11111110 +
b111 #
b111 )
b111 &
#3440
b11111101 !
b11111101 +
b1000 #
b1000 )
b1000 &
#3450
b11111100 !
b11111100 +
b1001 #
b1001 )
b1001 &
#3460
b11111011 !
b11111011 +
b1010 #
b1010 )
b1010 &
#3470
b11111010 !
b11111010 +
b1011 #
b1011 )
b1011 &
#3480
b11111001 !
b11111001 +
b1100 #
b1100 )
b1100 &
#3490
b11111000 !
b11111000 +
b1101 #
b1101 )
b1101 &
#3500
b11110111 !
b11110111 +
b1110 #
b1110 )
b1110 &
#3510
b11110110 !
b11110110 +
b1111 #
b1111 )
b1111 &
#3520
b110 !
b110 +
b0 #
b0 )
b110 "
b110 (
b110 %
b0 &
#3530
b101 !
b101 +
b1 #
b1 )
b1 &
#3540
b100 !
b100 +
b10 #
b10 )
b10 &
#3550
b11 !
b11 +
b11 #
b11 )
b11 &
#3560
b10 !
b10 +
b100 #
b100 )
b100 &
#3570
b1 !
b1 +
b101 #
b101 )
b101 &
#3580
b0 !
b0 +
b110 #
b110 )
b110 &
#3590
b11111111 !
b11111111 +
b111 #
b111 )
b111 &
#3600
b11111110 !
b11111110 +
b1000 #
b1000 )
b1000 &
#3610
b11111101 !
b11111101 +
b1001 #
b1001 )
b1001 &
#3620
b11111100 !
b11111100 +
b1010 #
b1010 )
b1010 &
#3630
b11111011 !
b11111011 +
b1011 #
b1011 )
b1011 &
#3640
b11111010 !
b11111010 +
b1100 #
b1100 )
b1100 &
#3650
b11111001 !
b11111001 +
b1101 #
b1101 )
b1101 &
#3660
b11111000 !
b11111000 +
b1110 #
b1110 )
b1110 &
#3670
b11110111 !
b11110111 +
b1111 #
b1111 )
b1111 &
#3680
b111 !
b111 +
b0 #
b0 )
b111 "
b111 (
b111 %
b0 &
#3690
b110 !
b110 +
b1 #
b1 )
b1 &
#3700
b101 !
b101 +
b10 #
b10 )
b10 &
#3710
b100 !
b100 +
b11 #
b11 )
b11 &
#3720
b11 !
b11 +
b100 #
b100 )
b100 &
#3730
b10 !
b10 +
b101 #
b101 )
b101 &
#3740
b1 !
b1 +
b110 #
b110 )
b110 &
#3750
b0 !
b0 +
b111 #
b111 )
b111 &
#3760
b11111111 !
b11111111 +
b1000 #
b1000 )
b1000 &
#3770
b11111110 !
b11111110 +
b1001 #
b1001 )
b1001 &
#3780
b11111101 !
b11111101 +
b1010 #
b1010 )
b1010 &
#3790
b11111100 !
b11111100 +
b1011 #
b1011 )
b1011 &
#3800
b11111011 !
b11111011 +
b1100 #
b1100 )
b1100 &
#3810
b11111010 !
b11111010 +
b1101 #
b1101 )
b1101 &
#3820
b11111001 !
b11111001 +
b1110 #
b1110 )
b1110 &
#3830
b11111000 !
b11111000 +
b1111 #
b1111 )
b1111 &
#3840
b1000 !
b1000 +
b0 #
b0 )
b1000 "
b1000 (
b1000 %
b0 &
#3850
b111 !
b111 +
b1 #
b1 )
b1 &
#3860
b110 !
b110 +
b10 #
b10 )
b10 &
#3870
b101 !
b101 +
b11 #
b11 )
b11 &
#3880
b100 !
b100 +
b100 #
b100 )
b100 &
#3890
b11 !
b11 +
b101 #
b101 )
b101 &
#3900
b10 !
b10 +
b110 #
b110 )
b110 &
#3910
b1 !
b1 +
b111 #
b111 )
b111 &
#3920
b0 !
b0 +
b1000 #
b1000 )
b1000 &
#3930
b11111111 !
b11111111 +
b1001 #
b1001 )
b1001 &
#3940
b11111110 !
b11111110 +
b1010 #
b1010 )
b1010 &
#3950
b11111101 !
b11111101 +
b1011 #
b1011 )
b1011 &
#3960
b11111100 !
b11111100 +
b1100 #
b1100 )
b1100 &
#3970
b11111011 !
b11111011 +
b1101 #
b1101 )
b1101 &
#3980
b11111010 !
b11111010 +
b1110 #
b1110 )
b1110 &
#3990
b11111001 !
b11111001 +
b1111 #
b1111 )
b1111 &
#4000
b1001 !
b1001 +
b0 #
b0 )
b1001 "
b1001 (
b1001 %
b0 &
#4010
b1000 !
b1000 +
b1 #
b1 )
b1 &
#4020
b111 !
b111 +
b10 #
b10 )
b10 &
#4030
b110 !
b110 +
b11 #
b11 )
b11 &
#4040
b101 !
b101 +
b100 #
b100 )
b100 &
#4050
b100 !
b100 +
b101 #
b101 )
b101 &
