fulladder/fulladder.v
// full adder
module fulladder (a,b,c,sum,carry);
    input a,b,c;
    output sum,carry;

    assign sum = a^b^c;
    assign carry = (a&b) | (c&(a^b));

endmodule

fulladder/tb_fulladder.v
//Full Adder test bench
module tb_fulladder;
    reg a,b,c;
    wire sum, carry;

    fulladder uut(
        .a(a), .b(b), .c(c),
        .sum(sum), .carry(carry)
    );

    initial begin

        $dumpfile("fulladder.vcd");
        $dumpvars(0, tb_fulladder);

        a=0; b=0; c=0; #10;
        a=0; b=0; c=1; #10;
        a=0; b=1; c=0; #10;
        a=0; b=1; c=1; #10;
        a=1; b=0; c=0; #10;
        a=1; b=0; c=1; #10;
        a=1; b=1; c=0; #10;
        a=1; b=1; c=1; #10;
        $finish;
    end
endmodule

fulladder/fulladder.vcd
$date
	Mon May 11 10:16:46 2026
$end
$version
	Icarus Verilog
$end
$timescale
	1s
$end
$scope module tb_fulladder $end
$var wire 1 ! sum $end
$var wire 1 " carry $end
$var reg 1 # a $end
$var reg 1 $ b $end
$var reg 1 % c $end
$scope module uut $end
$var wire 1 # a $end
$var wire 1 $ b $end
$var wire 1 % c $end
$var wire 1 " carry $end
$var wire 1 ! sum $end
$upscope $end
$upscope $end
$enddefinitions $end
$comment Show the parameter values. $end
$dumpall
$end
#0
$dumpvars
0%
0$
0#
0"
0!
$end
#10
1!
1%
#20
0%
1$
#30
1"
0!
1%
#40
0"
1!
0%
0$
1#
#50
1"
0!
1%
#60
0%
1$
#70
1!
1%
